gaddlemaps/__init__.py
gaddlemaps/__main__.py
gaddlemaps/_alignment.py
gaddlemaps/_auxilliary.py
gaddlemaps/_backend.py
gaddlemaps/_cli.py
gaddlemaps/_exchage_map.py
gaddlemaps/_manager.py
gaddlemaps/_represent.py
gaddlemaps/_transform_molecule.py
gaddlemaps/components/__init__.py
gaddlemaps/components/_components.py
gaddlemaps/components/_components_top.py
gaddlemaps/components/_residue.py
gaddlemaps/components/_system.py
gaddlemaps/data/BF4_AA.gro
gaddlemaps/data/BF4_AA.itp
gaddlemaps/data/BF4_CG.gro
gaddlemaps/data/BF4_CG.itp
gaddlemaps/data/BMIM_AA.gro
gaddlemaps/data/BMIM_AA.itp
gaddlemaps/data/BMIM_CG.itp
gaddlemaps/data/CUR_AA.gro
gaddlemaps/data/CUR_AA.itp
gaddlemaps/data/CUR_CG.itp
gaddlemaps/data/CUR_map.gro
gaddlemaps/data/DNA_AA.gro
gaddlemaps/data/DNA_AA.itp
gaddlemaps/data/DNA_CG.itp
gaddlemaps/data/DNA_map.gro
gaddlemaps/data/DPSM_AA.gro
gaddlemaps/data/DPSM_AA.itp
gaddlemaps/data/DPSM_CG.itp
gaddlemaps/data/Protein_AA.gro
gaddlemaps/data/Protein_AA.itp
gaddlemaps/data/Protein_CG.gro
gaddlemaps/data/Protein_CG.itp
gaddlemaps/data/SDS_AA.itp
gaddlemaps/data/VTE_AA.gro
gaddlemaps/data/VTE_AA.itp
gaddlemaps/data/VTE_map.gro
gaddlemaps/data/popc-AA.gro
gaddlemaps/data/popc-AA.itp
gaddlemaps/data/system_CG.gro
gaddlemaps/data/system_bmimbf4_cg.gro
gaddlemaps/data/vitamin_E_CG.itp
gaddlemaps/parsers/__init__.py
gaddlemaps/parsers/_itp_parse.py
gaddlemaps/parsers/_top_parsers.py
gaddlemaps-0.2.dist-info/LICENSE
gaddlemaps-0.2.dist-info/METADATA
gaddlemaps-0.2.dist-info/WHEEL
gaddlemaps-0.2.dist-info/entry_points.txt
gaddlemaps-0.2.dist-info/top_level.txt
gaddlemaps-0.2.dist-info/RECORD
