Metadata-Version: 2.1
Name: gaddlemaps
Version: 0.2
Summary: Python package to apply the GADDLE-MAPS algorithm
Home-page: https://github.com/txemaotero/gaddlemaps
Author: Jose Manuel Otero Mato, Hadrián Montes Campos, Luis Miguel Varela Cabo
Author-email: hadrianmontes@gmail.com, josemanuel.otero.mato@gmail.com
Project-URL: Documentation, https://gaddlemaps.readthedocs.io/
Project-URL: Source, https://github.com/txemaotero/gaddlemaps
Project-URL: Tracker, https://github.com/txemaotero/gaddlemaps/issues
Project-URL: Developed in, https://www.usc.gal/en
Project-URL: Cite, https://doi.org/10.1021/acs.jctc.7b00861
Classifier: Programming Language :: Python :: 3
Classifier: License :: OSI Approved :: GNU Affero General Public License v3 or later (AGPLv3+)
Classifier: Operating System :: OS Independent
Requires-Python: >=3.6
License-File: LICENSE
Requires-Dist: numpy
Requires-Dist: scipy
Requires-Dist: more-itertools
Requires-Dist: ipywidgets
